{"bg":{"type":"container","layer":0,"y":0,"x":0,"h":320,"w":800,"hidden":1,"click":0,"click_resp_msg":"0xE002","align_mode":21,"align_with":255},"objs":{"head_bg":{"type":"container","id":200,"x":138,"y":64,"w":524,"h":64,"in_type":0,"in_which_obj":255,"in_which_tab":255,"align_y_offset":0,"align_x_offset":0,"align_mode":21,"align_with":255,"hidden":0,"in_which_btn":255,"init_func":"","exit_func":"","hor_fit":0,"ver_fit":0,"layout":0,"style_idx":115,"click_resp_msg":"0xFFFF","catch_event":0,"link":"","click":1},"head_label":{"type":"label","id":201,"x":162,"y":0,"w":200,"h":64,"in_type":1,"in_which_obj":200,"in_which_tab":255,"align_y_offset":0,"align_x_offset":0,"align_mode":0,"align_with":200,"hidden":0,"in_which_btn":255,"init_func":"","exit_func":"","name":"STR_SETTINGS_LANGUAGE","style_idx":65535,"click":1,"long_mode":0,"font_size":255,"text_align":0},"line_4":{"type":"line","id":202,"x":0,"y":0,"w":0,"h":0,"in_type":0,"in_which_obj":255,"in_which_tab":255,"align_y_offset":0,"align_x_offset":0,"align_mode":21,"align_with":255,"hidden":0,"in_which_btn":255,"init_func":"","exit_func":"","points":[[138,126],[661,126]],"auto_size":1,"y_inv":0,"style_idx":116,"click":1},"setting":{"type":"list","id":203,"x":138,"y":128,"w":524,"h":192,"in_type":0,"in_which_obj":255,"in_which_tab":255,"align_y_offset":0,"align_x_offset":0,"align_mode":21,"align_with":255,"hidden":0,"in_which_btn":255,"init_func":"","exit_func":"","anim_time":100,"sb_mode":0,"options":["List 1","List 2","List 3"],"style_bg_idx":65535,"style_scrl_idx":65535,"style_sb_idx":65535,"style_rel_idx":108,"style_pr_idx":109,"style_tgl_rel_idx":65535,"style_tgl_pr_idx":65535,"style_ina_idx":65535,"has_link":0,"options_links":["0.json"],"options_num":7,"options_w":524,"options_h":64,"click_resp_msg":"0xE913","sel_btn":-1},"label_6":{"type":"label","id":205,"x":68,"y":20,"w":200,"h":64,"in_type":5,"in_which_obj":203,"in_which_tab":255,"align_y_offset":0,"align_x_offset":0,"align_mode":21,"align_with":255,"hidden":0,"in_which_btn":0,"init_func":"","exit_func":"","name":"STR_SETTINGS_LANGUAGE_ENGLISH","style_idx":65535,"click":1,"long_mode":1,"font_size":255,"text_align":0},"label_7":{"type":"label","id":206,"x":68,"y":20,"w":200,"h":64,"in_type":5,"in_which_obj":203,"in_which_tab":255,"align_y_offset":0,"align_x_offset":0,"align_mode":21,"align_with":255,"hidden":0,"in_which_btn":1,"init_func":"","exit_func":"","name":"STR_SETTINGS_LANGUAGE_SC","style_idx":65535,"click":1,"long_mode":1,"font_size":255,"text_align":0},"label_8":{"type":"label","id":207,"x":68,"y":20,"w":200,"h":64,"in_type":5,"in_which_obj":203,"in_which_tab":255,"align_y_offset":0,"align_x_offset":0,"align_mode":21,"align_with":255,"hidden":0,"in_which_btn":2,"init_func":"","exit_func":"","name":"STR_SETTINGS_LANGUAGE_TC","style_idx":65535,"click":1,"long_mode":1,"font_size":255,"text_align":0},"selected":{"type":"img","id":210,"x":400,"y":20,"w":21,"h":21,"in_type":5,"in_which_obj":203,"in_which_tab":255,"align_y_offset":0,"align_x_offset":0,"align_mode":21,"align_with":255,"hidden":0,"in_which_btn":255,"init_func":"language_init","exit_func":"language_exit","src_type":1,"src":"V:/image/04_setting_select.png.BGRA8888.ez","auto_size":1,"color_format":5,"style_idx":65535,"src_list":["0.png.BGRA8888.ez"]},"label_10":{"type":"label","id":208,"x":68,"y":20,"w":200,"h":64,"in_type":5,"in_which_obj":203,"in_which_tab":255,"align_y_offset":0,"align_x_offset":0,"align_mode":21,"align_with":255,"hidden":0,"in_which_btn":3,"init_func":"","exit_func":"","name":"STR_SETTINGS_LANGUAGE_JAP","style_idx":65535,"click":1,"long_mode":1,"font_size":255,"text_align":0},"label_11":{"type":"label","id":209,"x":68,"y":20,"w":200,"h":64,"in_type":5,"in_which_obj":203,"in_which_tab":255,"align_y_offset":0,"align_x_offset":0,"align_mode":21,"align_with":255,"hidden":0,"in_which_btn":4,"init_func":"","exit_func":"","name":"STR_SETTINGS_LANGUAGE_RUS","style_idx":65535,"click":1,"long_mode":1,"font_size":255,"text_align":0},"label_12":{"type":"label","id":211,"x":68,"y":20,"w":200,"h":64,"in_type":5,"in_which_obj":203,"in_which_tab":255,"align_y_offset":0,"align_x_offset":0,"align_mode":21,"align_with":255,"hidden":0,"in_which_btn":5,"init_func":"","exit_func":"","name":"STR_SETTINGS_LANGUAGE_THA","style_idx":65535,"click":1,"long_mode":1,"font_size":255,"text_align":0},"label_13":{"type":"label","id":212,"x":68,"y":20,"w":200,"h":64,"in_type":5,"in_which_obj":203,"in_which_tab":255,"align_y_offset":0,"align_x_offset":0,"align_mode":21,"align_with":255,"hidden":0,"in_which_btn":6,"init_func":"","exit_func":"","name":"STR_SETTINGS_LANGUAGE_CRAN","style_idx":65535,"click":1,"long_mode":1,"font_size":255,"text_align":0}}}