{"bg":{"layer":0,"type":"container","x":0,"y":0,"w":800,"h":320,"hidden":1,"click":"0","click_resp_msg":"0x0E7A1","align_mode":"21","align_with":"255"},"objs":{"cmdbar":{"type":"container","id":310,"x":0,"y":262,"w":800,"h":49,"init_func":"image_init","exit_func":"image_exit","in_type":"0","in_which_obj":"255","in_which_tab":"255","align_y_offset":"0","align_x_offset":"0","align_mode":"0","align_with":"0","hidden":1,"hor_fit":"0","ver_fit":"0","layout":"0","style_idx":"0","in_which_btn":"255","click_resp_msg":"0xFFFF","catch_event":"0","link":"0","click":"1"},"prev_imgbtn":{"type":"imgbtn","id":301,"x":236,"y":5,"w":40,"h":40,"in_type":1,"in_which_obj":310,"rel_img_type":1,"rel_img":"V:/image/03_file_explorer_play_skip_prev.png.BGRA8888.ez","pr_img_type":1,"pr_img":"V:/image/03_file_explorer_play_skip_prev.png.BGRA8888.ez","tgl_rel_img_type":1,"tgl_rel_img":"V:/image/03_file_explorer_play_skip_prev.png.BGRA8888.ez","tgl_pr_img_type":1,"tgl_pr_img":"V:/image/03_file_explorer_play_skip_prev.png.BGRA8888.ez","click_resp_msg":"0xE781","in_which_tab":"255","align_y_offset":"0","align_x_offset":"0","align_with":"0","hidden":"0","align_mode":"0","ina_img_type":"1","ina_img":"0","name":"","link":"0","pr_resp_msg":"0x0000","long_pr_resp_msg":"0x0000","long_pr_repeat_msg":"0x0000","txt_layout":"1","b_has_link":"0","is_ret":"0","style_rel_idx":"0","style_pr_idx":"0","style_tgl_rel_idx":"0","style_tgl_pr_idx":"0","style_ina_idx":"0","has_dialog":"0","iso_dialog":"0","pr_init":"0","rel_img_list":"","pr_img_list":"","in_which_btn":"0","init_func":"","exit_func":"","txt_offset_x":"0","txt_offset_y":"0","font_size":"10","txt_long_mode":"0","txt_align":"0","state":"0"},"next_imgbtn":{"type":"imgbtn","id":303,"x":512,"y":5,"w":40,"h":40,"in_type":1,"in_which_obj":310,"rel_img_type":1,"rel_img":"V:/image/03_file_explorer_play_skip_next.png.BGRA8888.ez","pr_img_type":1,"pr_img":"V:/image/03_file_explorer_play_skip_next.png.BGRA8888.ez","tgl_rel_img_type":1,"tgl_rel_img":"V:/image/03_file_explorer_play_skip_next.png.BGRA8888.ez","tgl_pr_img_type":1,"tgl_pr_img":"V:/image/03_file_explorer_play_skip_next.png.BGRA8888.ez","click_resp_msg":"0xE780","in_which_tab":"255","align_y_offset":"0","align_x_offset":"0","align_with":"0","hidden":"0","align_mode":"0","ina_img_type":"1","ina_img":"0","name":"","link":"0","pr_resp_msg":"0x0000","long_pr_resp_msg":"0x0000","long_pr_repeat_msg":"0x0000","txt_layout":"1","b_has_link":"0","is_ret":"0","style_rel_idx":"0","style_pr_idx":"0","style_tgl_rel_idx":"0","style_tgl_pr_idx":"0","style_ina_idx":"0","has_dialog":"0","iso_dialog":"0","pr_init":"0","rel_img_list":"","pr_img_list":"","in_which_btn":"0","init_func":"","exit_func":"","txt_offset_x":"0","txt_offset_y":"0","font_size":"10","txt_long_mode":"0","txt_align":"0","state":"0"}}}